setup.py
src/digimat/__init__.py
src/digimat.telegram.egg-info/PKG-INFO
src/digimat.telegram.egg-info/SOURCES.txt
src/digimat.telegram.egg-info/dependency_links.txt
src/digimat.telegram.egg-info/namespace_packages.txt
src/digimat.telegram.egg-info/not-zip-safe
src/digimat.telegram.egg-info/requires.txt
src/digimat.telegram.egg-info/top_level.txt
src/digimat/telegram/__init__.py
src/digimat/telegram/bot.py