Metadata-Version: 1.0
Name: digimat.telegram
Version: 0.1.4
Summary: Digimat Telegram Bot
Home-page: http://www.digimat.ch
Author: Frederic Hess
Author-email: fhess@splust.ch
License: PSF
Platform: UNKNOWN
